{
    "type": "endereco_numero",
    "values": {
        "endereco": "",
        "numero": "",
        "complemento": "S\/N"
    },
    "totalCount": 53,
    "usuario_email": "wellinghton90@gmail.com",
    "results": {
        "allResults": [
            {
                "id": 3277,
                "inscricao": 885165672015800,
                "imob_id": 11748,
                "logradouro": "RUA   JASPER  BRESLER",
                "numero": "325",
                "complemento": "S\/N",
                "bairro": "BELA VISTA",
                "cara_quarteirao": "141",
                "quadra": "S\/D",
                "lote": null,
                "total_construido": 216,
                "nome_pessoa": "TREVENZOLLI TERR. PAV. CONSTR. E COM. LTDA.",
                "cpf": null,
                "cnpj": "45.988.128\/0001-43",
                "area_terreno": "6000.00",
                "tipo_edificacao": "Edificado",
                "tipo_utilizacao": "Residencial",
                "zona": "ZUM2",
                "cat_via": " ECS2",
                "nome_loteamento": "885165 - SITIO SANTA ROSA",
                "imob_id_principal": 11748,
                "multiplo": 1,
                "uso_imovel": "Residencial",
                "historico": null,
                "desenho_id": null
            },
            {
                "id": 3307,
                "inscricao": 890165023087600,
                "imob_id": 129764,
                "logradouro": "RUA   JASPER  BRESLER",
                "numero": "441",
                "complemento": "S\/N",
                "bairro": "BELA VISTA",
                "cara_quarteirao": "141",
                "quadra": "S\/D",
                "lote": "D",
                "total_construido": 326,
                "nome_pessoa": "LUIZ TREVENZOLLI",
                "cpf": "023.449.478-68",
                "cnpj": null,
                "area_terreno": "4684.15",
                "tipo_edificacao": "Fechada",
                "tipo_utilizacao": "Residencial",
                "zona": "ZUM2",
                "cat_via": " ECS2",
                "nome_loteamento": "885165 - SITIO SANTA ROSA",
                "imob_id_principal": 129764,
                "multiplo": 1,
                "uso_imovel": "Residencial",
                "historico": null,
                "desenho_id": 778391
            },
            {
                "id": 3307,
                "inscricao": 890165023087600,
                "imob_id": 129764,
                "logradouro": "RUA   JASPER  BRESLER",
                "numero": "441",
                "complemento": "S\/N",
                "bairro": "BELA VISTA",
                "cara_quarteirao": "141",
                "quadra": "S\/D",
                "lote": "D",
                "total_construido": 326,
                "nome_pessoa": "LUIZ TREVENZOLLI",
                "cpf": "023.449.478-68",
                "cnpj": null,
                "area_terreno": "4684.15",
                "tipo_edificacao": "Fechada",
                "tipo_utilizacao": "Residencial",
                "zona": "ZUM2",
                "cat_via": " ECS2",
                "nome_loteamento": "885165 - SITIO SANTA ROSA",
                "imob_id_principal": 129764,
                "multiplo": 1,
                "uso_imovel": "Residencial",
                "historico": null,
                "desenho_id": 804862
            },
            {
                "id": 3350,
                "inscricao": 400150404050300,
                "imob_id": 15975,
                "logradouro": ".   CAMINHO DE SERVIDAO",
                "numero": "0",
                "complemento": "S\/N",
                "bairro": "BELA VISTA",
                "cara_quarteirao": "144",
                "quadra": "S\/D",
                "lote": "S\/N",
                "total_construido": 156,
                "nome_pessoa": "MAICK DE SOUZA LUCIZANO",
                "cpf": null,
                "cnpj": null,
                "area_terreno": "1000.00",
                "tipo_edificacao": "Edificado",
                "tipo_utilizacao": "Residencial",
                "zona": "ZUM2",
                "cat_via": " L",
                "nome_loteamento": "885165 - SITIO SANTA ROSA",
                "imob_id_principal": 15975,
                "multiplo": 1,
                "uso_imovel": "Residencial",
                "historico": null,
                "desenho_id": null
            },
            {
                "id": 10712,
                "inscricao": 905140921002300,
                "imob_id": 143075,
                "logradouro": "RUA   SUIÇA",
                "numero": "35",
                "complemento": "S\/N",
                "bairro": "JARDIM AMERICA",
                "cara_quarteirao": "380",
                "quadra": "M",
                "lote": "2A",
                "total_construido": 42,
                "nome_pessoa": "JOSE ALBERTO DE OLIVEIRA.",
                "cpf": "024.411.746-22",
                "cnpj": null,
                "area_terreno": "196.24",
                "tipo_edificacao": "Edificado",
                "tipo_utilizacao": "Residencial",
                "zona": "ZR2",
                "cat_via": " L",
                "nome_loteamento": "920160 - METROPOLITAN PARK",
                "imob_id_principal": 143075,
                "multiplo": 1,
                "uso_imovel": "Residencial",
                "historico": null,
                "desenho_id": 801756
            },
            {
                "id": 10713,
                "inscricao": 905140924029700,
                "imob_id": 143076,
                "logradouro": "RUA   ESCOCIA",
                "numero": "17",
                "complemento": "S\/N",
                "bairro": "JARDIM AMERICA",
                "cara_quarteirao": "380",
                "quadra": "M",
                "lote": "2B",
                "total_construido": 217,
                "nome_pessoa": "JOSE ALBERTO DE OLIVEIRA.",
                "cpf": "024.411.746-22",
                "cnpj": null,
                "area_terreno": "232.96",
                "tipo_edificacao": "Edificado",
                "tipo_utilizacao": "Residencial",
                "zona": "ZR2",
                "cat_via": " L",
                "nome_loteamento": "920160 - METROPOLITAN PARK",
                "imob_id_principal": 143076,
                "multiplo": 1,
                "uso_imovel": "Residencial",
                "historico": null,
                "desenho_id": 801755
            },
            {
                "id": 12726,
                "inscricao": 860160585063300,
                "imob_id": 14983,
                "logradouro": "AVN   NATANAEL JOSE DE CAMPOS",
                "numero": "109",
                "complemento": "S\/N",
                "bairro": "NOVA VENEZA",
                "cara_quarteirao": "445",
                "quadra": "B",
                "lote": "5",
                "total_construido": 0,
                "nome_pessoa": "ANTONIO JESUS ARGENTIN",
                "cpf": "083.278.898-85",
                "cnpj": null,
                "area_terreno": "1000.00",
                "tipo_edificacao": "Construção Em Andamento",
                "tipo_utilizacao": "Residencial",
                "zona": "ZR1",
                "cat_via": " ECS1",
                "nome_loteamento": "860160 - RECANTO FELIZ",
                "imob_id_principal": 14983,
                "multiplo": 1,
                "uso_imovel": "Residencial",
                "historico": null,
                "desenho_id": 748856
            },
            {
                "id": 12762,
                "inscricao": 865165203057300,
                "imob_id": 15875,
                "logradouro": "RUA   MARIA CONCEICAO DE CAMPOS",
                "numero": "113",
                "complemento": "S\/N",
                "bairro": "NOVA VENEZA",
                "cara_quarteirao": "448",
                "quadra": "E",
                "lote": "13",
                "total_construido": 140,
                "nome_pessoa": "FERNANDA MARTINATI ARAUJO",
                "cpf": "286.942.438-81",
                "cnpj": null,
                "area_terreno": "1155.70",
                "tipo_edificacao": "Edificado",
                "tipo_utilizacao": "Residencial",
                "zona": "ZR1",
                "cat_via": " ECS1",
                "nome_loteamento": "860160 - RECANTO FELIZ",
                "imob_id_principal": 15875,
                "multiplo": 1,
                "uso_imovel": "Residencial",
                "historico": null,
                "desenho_id": 748918
            },
            {
                "id": 12762,
                "inscricao": 865165203057300,
                "imob_id": 15875,
                "logradouro": "RUA   MARIA CONCEICAO DE CAMPOS",
                "numero": "113",
                "complemento": "S\/N",
                "bairro": "NOVA VENEZA",
                "cara_quarteirao": "448",
                "quadra": "E",
                "lote": "13",
                "total_construido": 140,
                "nome_pessoa": "FERNANDA MARTINATI ARAUJO",
                "cpf": "286.942.438-81",
                "cnpj": null,
                "area_terreno": "1155.70",
                "tipo_edificacao": "Edificado",
                "tipo_utilizacao": "Residencial",
                "zona": "ZR1",
                "cat_via": " ECS1",
                "nome_loteamento": "860160 - RECANTO FELIZ",
                "imob_id_principal": 15875,
                "multiplo": 1,
                "uso_imovel": "Residencial",
                "historico": null,
                "desenho_id": 758375
            },
            {
                "id": 12773,
                "inscricao": 865165202037900,
                "imob_id": 15870,
                "logradouro": "RUA   ANTONIO DOMINGOS CAMELLINI",
                "numero": "361",
                "complemento": "S\/N",
                "bairro": "NOVA VENEZA",
                "cara_quarteirao": "448",
                "quadra": "E",
                "lote": "20",
                "total_construido": 145,
                "nome_pessoa": "JOSE BENEDITO CAPELLOTI.",
                "cpf": "282.854.928-34",
                "cnpj": null,
                "area_terreno": "1000.00",
                "tipo_edificacao": "Edificado",
                "tipo_utilizacao": "Residencial",
                "zona": "ZR1",
                "cat_via": " L",
                "nome_loteamento": "860160 - RECANTO FELIZ",
                "imob_id_principal": 15870,
                "multiplo": 1,
                "uso_imovel": "Residencial",
                "historico": null,
                "desenho_id": 758387
            },
            {
                "id": 17011,
                "inscricao": 880170061002500,
                "imob_id": 13625,
                "logradouro": "RUA   MTO SALVADOR BOVE",
                "numero": "0",
                "complemento": "S\/N",
                "bairro": "JARDIM PLANALTO",
                "cara_quarteirao": "615",
                "quadra": "P",
                "lote": "1",
                "total_construido": 0,
                "nome_pessoa": "PREFEITURA MUNICIPAL DE PAULINIA",
                "cpf": null,
                "cnpj": "45.751.435\/0001-06",
                "area_terreno": "199.88",
                "tipo_edificacao": "Vago",
                "tipo_utilizacao": "Não Informado",
                "zona": "ZR3",
                "cat_via": " L",
                "nome_loteamento": "880171 - VILA NUNES",
                "imob_id_principal": 13625,
                "multiplo": 1,
                "uso_imovel": "?",
                "historico": null,
                "desenho_id": 769990
            },
            {
                "id": 17421,
                "inscricao": 885160672025300,
                "imob_id": 130003,
                "logradouro": "RUA   JASPER  BRESLER",
                "numero": "350",
                "complemento": "S\/N",
                "bairro": "BELA VISTA",
                "cara_quarteirao": "652",
                "quadra": "S\/D",
                "lote": "S\/D",
                "total_construido": 300,
                "nome_pessoa": "ESPOLIO DE ANTONIO VARANELLI",
                "cpf": "145.422.008-25",
                "cnpj": null,
                "area_terreno": "6800.00",
                "tipo_edificacao": "Edificado",
                "tipo_utilizacao": "Comercial",
                "zona": "ZUM2",
                "cat_via": " ECS2",
                "nome_loteamento": "885165 - SITIO SANTA ROSA",
                "imob_id_principal": 130003,
                "multiplo": 1,
                "uso_imovel": "Comercial",
                "historico": null,
                "desenho_id": 778247
            },
            {
                "id": 17423,
                "inscricao": 885160721006800,
                "imob_id": 130011,
                "logradouro": "RUA   JULIA VIEIRA",
                "numero": "0",
                "complemento": "S\/N",
                "bairro": "BELA VISTA",
                "cara_quarteirao": "653",
                "quadra": "S\/D",
                "lote": null,
                "total_construido": 329,
                "nome_pessoa": "LUIS CARLOS CADINE.",
                "cpf": "717.827.378-04",
                "cnpj": null,
                "area_terreno": "3630.00",
                "tipo_edificacao": "Edificado",
                "tipo_utilizacao": "Residencial",
                "zona": "ZUM2",
                "cat_via": " L",
                "nome_loteamento": "885165 - SITIO SANTA ROSA",
                "imob_id_principal": 130011,
                "multiplo": 1,
                "uso_imovel": "Residencial",
                "historico": null,
                "desenho_id": null
            },
            {
                "id": 17424,
                "inscricao": 885160721002500,
                "imob_id": 130009,
                "logradouro": "RUA   JULIA VIEIRA",
                "numero": "0",
                "complemento": "S\/N",
                "bairro": "BELA VISTA",
                "cara_quarteirao": "653",
                "quadra": "SD",
                "lote": null,
                "total_construido": 0,
                "nome_pessoa": "NELSON LETRINTA E OUTROS",
                "cpf": null,
                "cnpj": null,
                "area_terreno": "3000.00",
                "tipo_edificacao": "Vago",
                "tipo_utilizacao": "Não Informado",
                "zona": "ZUM2",
                "cat_via": " L",
                "nome_loteamento": "885165 - SITIO SANTA ROSA",
                "imob_id_principal": 130009,
                "multiplo": 1,
                "uso_imovel": "Não Informado",
                "historico": null,
                "desenho_id": null
            },
            {
                "id": 17443,
                "inscricao": 350150303014900,
                "imob_id": 131847,
                "logradouro": "AVN   PAULISTA",
                "numero": "747",
                "complemento": "S\/N",
                "bairro": "SAO LUIZ",
                "cara_quarteirao": "660",
                "quadra": "S\/D",
                "lote": "C",
                "total_construido": 46,
                "nome_pessoa": "ESPOLIO DE ARMANDO MILDES IGUARIO FILHO.",
                "cpf": "056.676.548-90",
                "cnpj": null,
                "area_terreno": "40768.83",
                "tipo_edificacao": "Edificado",
                "tipo_utilizacao": "Residencial",
                "zona": "ZR3",
                "cat_via": " ECS1",
                "nome_loteamento": "425155 - AREA DESMEMBRADA GLEBA C",
                "imob_id_principal": 131847,
                "multiplo": 1,
                "uso_imovel": "Residencial",
                "historico": null,
                "desenho_id": null
            },
            {
                "id": 23397,
                "inscricao": 865165741006400,
                "imob_id": 15053,
                "logradouro": "RUA   PLINIO NASCIMENTO",
                "numero": "60",
                "complemento": "S\/N",
                "bairro": "NOVA VENEZA",
                "cara_quarteirao": "927",
                "quadra": "S\/D",
                "lote": "49",
                "total_construido": 0,
                "nome_pessoa": "MARCIO RENATO MANGINI",
                "cpf": "172.109.518-73",
                "cnpj": null,
                "area_terreno": "2660.00",
                "tipo_edificacao": "Vago",
                "tipo_utilizacao": "Residencial",
                "zona": "ZR1",
                "cat_via": " L",
                "nome_loteamento": "865166 - PARQUE NOVA VENEZA",
                "imob_id_principal": 15053,
                "multiplo": 1,
                "uso_imovel": "Residencial",
                "historico": null,
                "desenho_id": 758433
            },
            {
                "id": 23406,
                "inscricao": 865165743073300,
                "imob_id": 15058,
                "logradouro": "RUA   JOSE CARLOS POGGETTI",
                "numero": "335",
                "complemento": "S\/N",
                "bairro": "NOVA VENEZA",
                "cara_quarteirao": "927",
                "quadra": "S\/D",
                "lote": "58",
                "total_construido": 0,
                "nome_pessoa": "ARNALDO AVELLAR",
                "cpf": "014.250.728-87",
                "cnpj": null,
                "area_terreno": "2646.00",
                "tipo_edificacao": "Vago",
                "tipo_utilizacao": "Não Informado",
                "zona": "ZR1",
                "cat_via": " ECS3",
                "nome_loteamento": "865166 - PARQUE NOVA VENEZA",
                "imob_id_principal": 15058,
                "multiplo": 1,
                "uso_imovel": "Não Informado",
                "historico": null,
                "desenho_id": 758430
            },
            {
                "id": 23407,
                "inscricao": 865165743070300,
                "imob_id": 15057,
                "logradouro": "RUA   JOSE CARLOS POGGETTI",
                "numero": "365",
                "complemento": "S\/N",
                "bairro": "NOVA VENEZA",
                "cara_quarteirao": "927",
                "quadra": "S\/D",
                "lote": "59",
                "total_construido": 140,
                "nome_pessoa": "ALTAIR ROBERTO DA FONSECA .",
                "cpf": "554.959.318-15",
                "cnpj": null,
                "area_terreno": "2646.00",
                "tipo_edificacao": "Edificado",
                "tipo_utilizacao": "Residencial",
                "zona": "ZR1",
                "cat_via": " ECS3",
                "nome_loteamento": "865166 - PARQUE NOVA VENEZA",
                "imob_id_principal": 15057,
                "multiplo": 1,
                "uso_imovel": "Residencial",
                "historico": null,
                "desenho_id": 758429
            },
            {
                "id": 23432,
                "inscricao": 865165353070900,
                "imob_id": 263234,
                "logradouro": "RUA   JOSE CARLOS POGGETTI",
                "numero": "354",
                "complemento": "S\/N",
                "bairro": "NOVA VENEZA",
                "cara_quarteirao": "928",
                "quadra": "S\/D",
                "lote": "32A3",
                "total_construido": 479,
                "nome_pessoa": "VALMOR AMORIM",
                "cpf": "416.768.230-34",
                "cnpj": null,
                "area_terreno": "10799.72",
                "tipo_edificacao": "Edificado",
                "tipo_utilizacao": "Residencial",
                "zona": "ZR1",
                "cat_via": " ECS1",
                "nome_loteamento": "865166 - PARQUE NOVA VENEZA",
                "imob_id_principal": 263234,
                "multiplo": 1,
                "uso_imovel": "Residencial",
                "historico": null,
                "desenho_id": null
            },
            {
                "id": 23433,
                "inscricao": 865165353062600,
                "imob_id": 263233,
                "logradouro": "RUA   JOSE CARLOS POGGETTI",
                "numero": "366",
                "complemento": "S\/N",
                "bairro": "NOVA VENEZA",
                "cara_quarteirao": "928",
                "quadra": "S\/D",
                "lote": "32A4",
                "total_construido": 0,
                "nome_pessoa": "VALMOR AMORIM",
                "cpf": "416.768.230-34",
                "cnpj": null,
                "area_terreno": "400.05",
                "tipo_edificacao": "Vago",
                "tipo_utilizacao": "Residencial",
                "zona": "ZR1",
                "cat_via": " ECS1",
                "nome_loteamento": "865166 - PARQUE NOVA VENEZA",
                "imob_id_principal": 263233,
                "multiplo": 1,
                "uso_imovel": "Residencial",
                "historico": null,
                "desenho_id": null
            },
            {
                "id": 23434,
                "inscricao": 865165353063800,
                "imob_id": 263232,
                "logradouro": "RUA   JOSE CARLOS POGGETTI",
                "numero": "378",
                "complemento": "S\/N",
                "bairro": "NOVA VENEZA",
                "cara_quarteirao": "928",
                "quadra": "S\/D",
                "lote": "32A5",
                "total_construido": 0,
                "nome_pessoa": "VALMOR AMORIM",
                "cpf": "416.768.230-34",
                "cnpj": null,
                "area_terreno": "400.05",
                "tipo_edificacao": "Vago",
                "tipo_utilizacao": "Residencial",
                "zona": "ZR1",
                "cat_via": " ECS1",
                "nome_loteamento": "865166 - PARQUE NOVA VENEZA",
                "imob_id_principal": 263232,
                "multiplo": 1,
                "uso_imovel": "Residencial",
                "historico": null,
                "desenho_id": null
            },
            {
                "id": 23435,
                "inscricao": 865165353065000,
                "imob_id": 263231,
                "logradouro": "RUA   JOSE CARLOS POGGETTI",
                "numero": "390",
                "complemento": "S\/N",
                "bairro": "NOVA VENEZA",
                "cara_quarteirao": "928",
                "quadra": "S\/D",
                "lote": "32A6",
                "total_construido": 0,
                "nome_pessoa": "VALMOR AMORIM",
                "cpf": "416.768.230-34",
                "cnpj": null,
                "area_terreno": "400.05",
                "tipo_edificacao": "Vago",
                "tipo_utilizacao": "Residencial",
                "zona": "ZR1",
                "cat_via": " ECS1",
                "nome_loteamento": "865166 - PARQUE NOVA VENEZA",
                "imob_id_principal": 263231,
                "multiplo": 1,
                "uso_imovel": "Residencial",
                "historico": null,
                "desenho_id": null
            },
            {
                "id": 23436,
                "inscricao": 865165353066200,
                "imob_id": 263230,
                "logradouro": "RUA   JOSE CARLOS POGGETTI",
                "numero": "402",
                "complemento": "S\/N",
                "bairro": "NOVA VENEZA",
                "cara_quarteirao": "928",
                "quadra": "S\/D",
                "lote": "32A7",
                "total_construido": 0,
                "nome_pessoa": "VALMOR AMORIM",
                "cpf": "416.768.230-34",
                "cnpj": null,
                "area_terreno": "400.05",
                "tipo_edificacao": "Vago",
                "tipo_utilizacao": "Residencial",
                "zona": "ZR1",
                "cat_via": " ECS1",
                "nome_loteamento": "865166 - PARQUE NOVA VENEZA",
                "imob_id_principal": 263230,
                "multiplo": 1,
                "uso_imovel": "Residencial",
                "historico": null,
                "desenho_id": null
            },
            {
                "id": 23437,
                "inscricao": 865165353067400,
                "imob_id": 263229,
                "logradouro": "RUA   JOSE CARLOS POGGETTI",
                "numero": "418",
                "complemento": "S\/N",
                "bairro": "NOVA VENEZA",
                "cara_quarteirao": "928",
                "quadra": "S\/D",
                "lote": "32A8",
                "total_construido": 0,
                "nome_pessoa": "VALMOR AMORIM",
                "cpf": "416.768.230-34",
                "cnpj": null,
                "area_terreno": "475.77",
                "tipo_edificacao": "Vago",
                "tipo_utilizacao": "Residencial",
                "zona": "ZR1",
                "cat_via": " ECS1",
                "nome_loteamento": "865166 - PARQUE NOVA VENEZA",
                "imob_id_principal": 263229,
                "multiplo": 1,
                "uso_imovel": "Residencial",
                "historico": null,
                "desenho_id": null
            },
            {
                "id": 23438,
                "inscricao": 865165353069000,
                "imob_id": 263228,
                "logradouro": "RUA   JOSE CARLOS POGGETTI",
                "numero": "438",
                "complemento": "S\/N",
                "bairro": "NOVA VENEZA",
                "cara_quarteirao": "928",
                "quadra": "S\/D",
                "lote": "32A9",
                "total_construido": 0,
                "nome_pessoa": "VALMOR AMORIM",
                "cpf": "416.768.230-34",
                "cnpj": null,
                "area_terreno": "560.08",
                "tipo_edificacao": "Vago",
                "tipo_utilizacao": "Residencial",
                "zona": "ZR1",
                "cat_via": " ECS1",
                "nome_loteamento": "865166 - PARQUE NOVA VENEZA",
                "imob_id_principal": 263228,
                "multiplo": 1,
                "uso_imovel": "Residencial",
                "historico": null,
                "desenho_id": null
            },
            {
                "id": 23446,
                "inscricao": 865165352049800,
                "imob_id": 131390,
                "logradouro": "RUA   JOSE CARLOS POGGETTI",
                "numero": "340",
                "complemento": "S\/N",
                "bairro": "NOVA VENEZA",
                "cara_quarteirao": "928",
                "quadra": "S\/D",
                "lote": "40",
                "total_construido": 73,
                "nome_pessoa": "SERGIO LUIZ DA FONSECA",
                "cpf": "963.287.628-87",
                "cnpj": null,
                "area_terreno": "2646.00",
                "tipo_edificacao": "Edificado",
                "tipo_utilizacao": "Residencial",
                "zona": "ZR1",
                "cat_via": " ECS3",
                "nome_loteamento": "865166 - PARQUE NOVA VENEZA",
                "imob_id_principal": 131390,
                "multiplo": 1,
                "uso_imovel": "Residencial",
                "historico": null,
                "desenho_id": 758406
            },
            {
                "id": 23446,
                "inscricao": 865165352049800,
                "imob_id": 131390,
                "logradouro": "RUA   JOSE CARLOS POGGETTI",
                "numero": "340",
                "complemento": "S\/N",
                "bairro": "NOVA VENEZA",
                "cara_quarteirao": "928",
                "quadra": "S\/D",
                "lote": "40",
                "total_construido": 73,
                "nome_pessoa": "SERGIO LUIZ DA FONSECA",
                "cpf": "963.287.628-87",
                "cnpj": null,
                "area_terreno": "2646.00",
                "tipo_edificacao": "Edificado",
                "tipo_utilizacao": "Residencial",
                "zona": "ZR1",
                "cat_via": " ECS3",
                "nome_loteamento": "865166 - PARQUE NOVA VENEZA",
                "imob_id_principal": 131390,
                "multiplo": 1,
                "uso_imovel": "Residencial",
                "historico": null,
                "desenho_id": 808101
            },
            {
                "id": 23448,
                "inscricao": 865165352043800,
                "imob_id": 131388,
                "logradouro": "RUA   JOSE CARLOS POGGETTI",
                "numero": "280",
                "complemento": "S\/N",
                "bairro": "NOVA VENEZA",
                "cara_quarteirao": "928",
                "quadra": "S\/D",
                "lote": "42",
                "total_construido": 0,
                "nome_pessoa": "SERGIO LUIZ DA FONSECA",
                "cpf": "963.287.628-87",
                "cnpj": null,
                "area_terreno": "2646.00",
                "tipo_edificacao": "Vago",
                "tipo_utilizacao": "Não Informado",
                "zona": "ZR1",
                "cat_via": " ECS3",
                "nome_loteamento": "865166 - PARQUE NOVA VENEZA",
                "imob_id_principal": 131388,
                "multiplo": 1,
                "uso_imovel": "Não Informado",
                "historico": null,
                "desenho_id": 758404
            },
            {
                "id": 23448,
                "inscricao": 865165352043800,
                "imob_id": 131388,
                "logradouro": "RUA   JOSE CARLOS POGGETTI",
                "numero": "280",
                "complemento": "S\/N",
                "bairro": "NOVA VENEZA",
                "cara_quarteirao": "928",
                "quadra": "S\/D",
                "lote": "42",
                "total_construido": 0,
                "nome_pessoa": "SERGIO LUIZ DA FONSECA",
                "cpf": "963.287.628-87",
                "cnpj": null,
                "area_terreno": "2646.00",
                "tipo_edificacao": "Vago",
                "tipo_utilizacao": "Não Informado",
                "zona": "ZR1",
                "cat_via": " ECS3",
                "nome_loteamento": "865166 - PARQUE NOVA VENEZA",
                "imob_id_principal": 131388,
                "multiplo": 1,
                "uso_imovel": "Não Informado",
                "historico": null,
                "desenho_id": 808080
            },
            {
                "id": 23449,
                "inscricao": 865165352040800,
                "imob_id": 131387,
                "logradouro": "RUA   JOSE CARLOS POGGETTI",
                "numero": "250",
                "complemento": "S\/N",
                "bairro": "NOVA VENEZA",
                "cara_quarteirao": "928",
                "quadra": "S\/D",
                "lote": "43",
                "total_construido": 0,
                "nome_pessoa": "LUIS FERNANDO BOSELLI DE SOUZA",
                "cpf": "287.209.218-88",
                "cnpj": null,
                "area_terreno": "2646.00",
                "tipo_edificacao": "Vago",
                "tipo_utilizacao": "Não Informado",
                "zona": "ZR1",
                "cat_via": " ECS3",
                "nome_loteamento": "865166 - PARQUE NOVA VENEZA",
                "imob_id_principal": 131387,
                "multiplo": 1,
                "uso_imovel": "Não Informado",
                "historico": null,
                "desenho_id": 758405
            },
            {
                "id": 23449,
                "inscricao": 865165352040800,
                "imob_id": 131387,
                "logradouro": "RUA   JOSE CARLOS POGGETTI",
                "numero": "250",
                "complemento": "S\/N",
                "bairro": "NOVA VENEZA",
                "cara_quarteirao": "928",
                "quadra": "S\/D",
                "lote": "43",
                "total_construido": 0,
                "nome_pessoa": "LUIS FERNANDO BOSELLI DE SOUZA",
                "cpf": "287.209.218-88",
                "cnpj": null,
                "area_terreno": "2646.00",
                "tipo_edificacao": "Vago",
                "tipo_utilizacao": "Não Informado",
                "zona": "ZR1",
                "cat_via": " ECS3",
                "nome_loteamento": "865166 - PARQUE NOVA VENEZA",
                "imob_id_principal": 131387,
                "multiplo": 1,
                "uso_imovel": "Não Informado",
                "historico": null,
                "desenho_id": 808064
            },
            {
                "id": 23492,
                "inscricao": 865170713052500,
                "imob_id": 129,
                "logradouro": "RUA   PLINIO NASCIMENTO",
                "numero": "600",
                "complemento": "S\/N",
                "bairro": "NOVA VENEZA",
                "cara_quarteirao": "930",
                "quadra": "S\/D",
                "lote": "13",
                "total_construido": 104,
                "nome_pessoa": "JOAO GERMANO BANCHIERI.",
                "cpf": "020.835.748-34",
                "cnpj": null,
                "area_terreno": "2502.00",
                "tipo_edificacao": "Edificado",
                "tipo_utilizacao": "Outros",
                "zona": "ZR1",
                "cat_via": " L",
                "nome_loteamento": "865166 - PARQUE NOVA VENEZA",
                "imob_id_principal": 129,
                "multiplo": 1,
                "uso_imovel": "Outros",
                "historico": null,
                "desenho_id": 758459
            },
            {
                "id": 23493,
                "inscricao": 865170713049600,
                "imob_id": 15890,
                "logradouro": "RUA   PLINIO NASCIMENTO",
                "numero": "570",
                "complemento": "S\/N",
                "bairro": "NOVA VENEZA",
                "cara_quarteirao": "930",
                "quadra": "S\/D",
                "lote": "14",
                "total_construido": 335,
                "nome_pessoa": "JOAO GERMANO BANCHIERI.",
                "cpf": "020.835.748-34",
                "cnpj": null,
                "area_terreno": "2403.40",
                "tipo_edificacao": "Edificado",
                "tipo_utilizacao": "Outros",
                "zona": "ZR1",
                "cat_via": " L",
                "nome_loteamento": "865166 - PARQUE NOVA VENEZA",
                "imob_id_principal": 15890,
                "multiplo": 1,
                "uso_imovel": "Outros",
                "historico": null,
                "desenho_id": 758458
            },
            {
                "id": 23507,
                "inscricao": 865170711013300,
                "imob_id": 15883,
                "logradouro": "RUA   PLINIO NASCIMENTO",
                "numero": "210",
                "complemento": "S\/N",
                "bairro": "NOVA VENEZA",
                "cara_quarteirao": "930",
                "quadra": "S\/D",
                "lote": "4",
                "total_construido": 280,
                "nome_pessoa": "CYNTHIA CRISTINA DE ANDRADE SIQUEIRA DO AMARAL",
                "cpf": "308.253.098-24",
                "cnpj": null,
                "area_terreno": "2502.00",
                "tipo_edificacao": "Edificado",
                "tipo_utilizacao": "Residencial",
                "zona": "ZR1",
                "cat_via": " L",
                "nome_loteamento": "865166 - PARQUE NOVA VENEZA",
                "imob_id_principal": 15883,
                "multiplo": 1,
                "uso_imovel": "Residencial",
                "historico": null,
                "desenho_id": 758455
            },
            {
                "id": 28317,
                "inscricao": 845180731011700,
                "imob_id": 15241,
                "logradouro": "RUA   LUDEVINA DE FREITAS",
                "numero": "26",
                "complemento": "S\/N",
                "bairro": "SALTINHO",
                "cara_quarteirao": "1140",
                "quadra": "S\/D",
                "lote": "10",
                "total_construido": 221,
                "nome_pessoa": "JORGE CURY",
                "cpf": null,
                "cnpj": null,
                "area_terreno": "1045.00",
                "tipo_edificacao": "Edificado",
                "tipo_utilizacao": "Residencial",
                "zona": "ZR3",
                "cat_via": " L",
                "nome_loteamento": "850180 - SUB-FERNANDO ARGENTIN",
                "imob_id_principal": 15241,
                "multiplo": 1,
                "uso_imovel": "Residencial",
                "historico": null,
                "desenho_id": 744535
            },
            {
                "id": 28317,
                "inscricao": 845180731011700,
                "imob_id": 15241,
                "logradouro": "RUA   LUDEVINA DE FREITAS",
                "numero": "26",
                "complemento": "S\/N",
                "bairro": "SALTINHO",
                "cara_quarteirao": "1140",
                "quadra": "S\/D",
                "lote": "10",
                "total_construido": 221,
                "nome_pessoa": "JORGE CURY",
                "cpf": null,
                "cnpj": null,
                "area_terreno": "1045.00",
                "tipo_edificacao": "Edificado",
                "tipo_utilizacao": "Residencial",
                "zona": "ZR3",
                "cat_via": " L",
                "nome_loteamento": "850180 - SUB-FERNANDO ARGENTIN",
                "imob_id_principal": 15241,
                "multiplo": 1,
                "uso_imovel": "Residencial",
                "historico": null,
                "desenho_id": 745558
            },
            {
                "id": 28317,
                "inscricao": 845180731011700,
                "imob_id": 15241,
                "logradouro": "RUA   LUDEVINA DE FREITAS",
                "numero": "26",
                "complemento": "S\/N",
                "bairro": "SALTINHO",
                "cara_quarteirao": "1140",
                "quadra": "S\/D",
                "lote": "10",
                "total_construido": 221,
                "nome_pessoa": "JORGE CURY",
                "cpf": null,
                "cnpj": null,
                "area_terreno": "1045.00",
                "tipo_edificacao": "Edificado",
                "tipo_utilizacao": "Residencial",
                "zona": "ZR3",
                "cat_via": " L",
                "nome_loteamento": "850180 - SUB-FERNANDO ARGENTIN",
                "imob_id_principal": 15241,
                "multiplo": 1,
                "uso_imovel": "Residencial",
                "historico": null,
                "desenho_id": 745578
            },
            {
                "id": 28317,
                "inscricao": 845180731011700,
                "imob_id": 15241,
                "logradouro": "RUA   LUDEVINA DE FREITAS",
                "numero": "26",
                "complemento": "S\/N",
                "bairro": "SALTINHO",
                "cara_quarteirao": "1140",
                "quadra": "S\/D",
                "lote": "10",
                "total_construido": 221,
                "nome_pessoa": "JORGE CURY",
                "cpf": null,
                "cnpj": null,
                "area_terreno": "1045.00",
                "tipo_edificacao": "Edificado",
                "tipo_utilizacao": "Residencial",
                "zona": "ZR3",
                "cat_via": " L",
                "nome_loteamento": "850180 - SUB-FERNANDO ARGENTIN",
                "imob_id_principal": 15241,
                "multiplo": 1,
                "uso_imovel": "Residencial",
                "historico": null,
                "desenho_id": 805083
            },
            {
                "id": 28317,
                "inscricao": 845180731011700,
                "imob_id": 15241,
                "logradouro": "RUA   LUDEVINA DE FREITAS",
                "numero": "26",
                "complemento": "S\/N",
                "bairro": "SALTINHO",
                "cara_quarteirao": "1140",
                "quadra": "S\/D",
                "lote": "10",
                "total_construido": 221,
                "nome_pessoa": "JORGE CURY",
                "cpf": null,
                "cnpj": null,
                "area_terreno": "1045.00",
                "tipo_edificacao": "Edificado",
                "tipo_utilizacao": "Residencial",
                "zona": "ZR3",
                "cat_via": " L",
                "nome_loteamento": "850180 - SUB-FERNANDO ARGENTIN",
                "imob_id_principal": 15241,
                "multiplo": 1,
                "uso_imovel": "Residencial",
                "historico": null,
                "desenho_id": 805111
            },
            {
                "id": 28318,
                "inscricao": 845180731010600,
                "imob_id": 15240,
                "logradouro": "RUA   LUDEVINA DE FREITAS",
                "numero": "14",
                "complemento": "S\/N",
                "bairro": "SALTINHO",
                "cara_quarteirao": "1140",
                "quadra": "S\/D",
                "lote": "11",
                "total_construido": 142,
                "nome_pessoa": "LORENZA FERNANDES PICHITELI",
                "cpf": null,
                "cnpj": null,
                "area_terreno": "1125.00",
                "tipo_edificacao": "Edificado",
                "tipo_utilizacao": "Residencial",
                "zona": "ZR3",
                "cat_via": " L",
                "nome_loteamento": "850180 - SUB-FERNANDO ARGENTIN",
                "imob_id_principal": 15240,
                "multiplo": 1,
                "uso_imovel": "Residencial",
                "historico": null,
                "desenho_id": 744536
            },
            {
                "id": 28318,
                "inscricao": 845180731010600,
                "imob_id": 15240,
                "logradouro": "RUA   LUDEVINA DE FREITAS",
                "numero": "14",
                "complemento": "S\/N",
                "bairro": "SALTINHO",
                "cara_quarteirao": "1140",
                "quadra": "S\/D",
                "lote": "11",
                "total_construido": 142,
                "nome_pessoa": "LORENZA FERNANDES PICHITELI",
                "cpf": null,
                "cnpj": null,
                "area_terreno": "1125.00",
                "tipo_edificacao": "Edificado",
                "tipo_utilizacao": "Residencial",
                "zona": "ZR3",
                "cat_via": " L",
                "nome_loteamento": "850180 - SUB-FERNANDO ARGENTIN",
                "imob_id_principal": 15240,
                "multiplo": 1,
                "uso_imovel": "Residencial",
                "historico": null,
                "desenho_id": 745559
            },
            {
                "id": 28318,
                "inscricao": 845180731010600,
                "imob_id": 15240,
                "logradouro": "RUA   LUDEVINA DE FREITAS",
                "numero": "14",
                "complemento": "S\/N",
                "bairro": "SALTINHO",
                "cara_quarteirao": "1140",
                "quadra": "S\/D",
                "lote": "11",
                "total_construido": 142,
                "nome_pessoa": "LORENZA FERNANDES PICHITELI",
                "cpf": null,
                "cnpj": null,
                "area_terreno": "1125.00",
                "tipo_edificacao": "Edificado",
                "tipo_utilizacao": "Residencial",
                "zona": "ZR3",
                "cat_via": " L",
                "nome_loteamento": "850180 - SUB-FERNANDO ARGENTIN",
                "imob_id_principal": 15240,
                "multiplo": 1,
                "uso_imovel": "Residencial",
                "historico": null,
                "desenho_id": 805087
            },
            {
                "id": 28318,
                "inscricao": 845180731010600,
                "imob_id": 15240,
                "logradouro": "RUA   LUDEVINA DE FREITAS",
                "numero": "14",
                "complemento": "S\/N",
                "bairro": "SALTINHO",
                "cara_quarteirao": "1140",
                "quadra": "S\/D",
                "lote": "11",
                "total_construido": 142,
                "nome_pessoa": "LORENZA FERNANDES PICHITELI",
                "cpf": null,
                "cnpj": null,
                "area_terreno": "1125.00",
                "tipo_edificacao": "Edificado",
                "tipo_utilizacao": "Residencial",
                "zona": "ZR3",
                "cat_via": " L",
                "nome_loteamento": "850180 - SUB-FERNANDO ARGENTIN",
                "imob_id_principal": 15240,
                "multiplo": 1,
                "uso_imovel": "Residencial",
                "historico": null,
                "desenho_id": 805108
            },
            {
                "id": 28325,
                "inscricao": 350150303009700,
                "imob_id": 15933,
                "logradouro": "PLN   ESTRADA DA SERVIDAO",
                "numero": "1905",
                "complemento": "S\/N",
                "bairro": "SALTINHO",
                "cara_quarteirao": "1140",
                "quadra": "S\/D",
                "lote": "3",
                "total_construido": 40,
                "nome_pessoa": "VALDEMAR MARES DE OLIVEIRA",
                "cpf": "080.893.965-34",
                "cnpj": null,
                "area_terreno": "2010.00",
                "tipo_edificacao": "Edificado",
                "tipo_utilizacao": "Residencial",
                "zona": "ZR3",
                "cat_via": " ECS2",
                "nome_loteamento": "410160 - FAZENDA SALTINHO",
                "imob_id_principal": 15933,
                "multiplo": 1,
                "uso_imovel": "Residencial",
                "historico": null,
                "desenho_id": 745550
            },
            {
                "id": 28325,
                "inscricao": 350150303009700,
                "imob_id": 15933,
                "logradouro": "PLN   ESTRADA DA SERVIDAO",
                "numero": "1905",
                "complemento": "S\/N",
                "bairro": "SALTINHO",
                "cara_quarteirao": "1140",
                "quadra": "S\/D",
                "lote": "3",
                "total_construido": 40,
                "nome_pessoa": "VALDEMAR MARES DE OLIVEIRA",
                "cpf": "080.893.965-34",
                "cnpj": null,
                "area_terreno": "2010.00",
                "tipo_edificacao": "Edificado",
                "tipo_utilizacao": "Residencial",
                "zona": "ZR3",
                "cat_via": " ECS2",
                "nome_loteamento": "410160 - FAZENDA SALTINHO",
                "imob_id_principal": 15933,
                "multiplo": 1,
                "uso_imovel": "Residencial",
                "historico": null,
                "desenho_id": 745552
            },
            {
                "id": 28325,
                "inscricao": 350150303009700,
                "imob_id": 15933,
                "logradouro": "PLN   ESTRADA DA SERVIDAO",
                "numero": "1905",
                "complemento": "S\/N",
                "bairro": "SALTINHO",
                "cara_quarteirao": "1140",
                "quadra": "S\/D",
                "lote": "3",
                "total_construido": 40,
                "nome_pessoa": "VALDEMAR MARES DE OLIVEIRA",
                "cpf": "080.893.965-34",
                "cnpj": null,
                "area_terreno": "2010.00",
                "tipo_edificacao": "Edificado",
                "tipo_utilizacao": "Residencial",
                "zona": "ZR3",
                "cat_via": " ECS2",
                "nome_loteamento": "410160 - FAZENDA SALTINHO",
                "imob_id_principal": 15933,
                "multiplo": 1,
                "uso_imovel": "Residencial",
                "historico": null,
                "desenho_id": 745556
            },
            {
                "id": 28325,
                "inscricao": 350150303009700,
                "imob_id": 15933,
                "logradouro": "PLN   ESTRADA DA SERVIDAO",
                "numero": "1905",
                "complemento": "S\/N",
                "bairro": "SALTINHO",
                "cara_quarteirao": "1140",
                "quadra": "S\/D",
                "lote": "3",
                "total_construido": 40,
                "nome_pessoa": "VALDEMAR MARES DE OLIVEIRA",
                "cpf": "080.893.965-34",
                "cnpj": null,
                "area_terreno": "2010.00",
                "tipo_edificacao": "Edificado",
                "tipo_utilizacao": "Residencial",
                "zona": "ZR3",
                "cat_via": " ECS2",
                "nome_loteamento": "410160 - FAZENDA SALTINHO",
                "imob_id_principal": 15933,
                "multiplo": 1,
                "uso_imovel": "Residencial",
                "historico": null,
                "desenho_id": 805060
            },
            {
                "id": 28327,
                "inscricao": 845180731019700,
                "imob_id": 15248,
                "logradouro": "RUA   LUDEVINA DE FREITAS",
                "numero": "100",
                "complemento": "S\/N",
                "bairro": "SALTINHO",
                "cara_quarteirao": "1140",
                "quadra": "S\/D",
                "lote": "3",
                "total_construido": 262,
                "nome_pessoa": "ROBERTO MARIO RODRIGUES MARTINS",
                "cpf": "409.036.998-34",
                "cnpj": null,
                "area_terreno": "1180.00",
                "tipo_edificacao": "Edificado",
                "tipo_utilizacao": "Residencial",
                "zona": "ZR3",
                "cat_via": " L",
                "nome_loteamento": "850180 - SUB-FERNANDO ARGENTIN",
                "imob_id_principal": 15248,
                "multiplo": 1,
                "uso_imovel": "Residencial",
                "historico": null,
                "desenho_id": 745550
            },
            {
                "id": 28327,
                "inscricao": 845180731019700,
                "imob_id": 15248,
                "logradouro": "RUA   LUDEVINA DE FREITAS",
                "numero": "100",
                "complemento": "S\/N",
                "bairro": "SALTINHO",
                "cara_quarteirao": "1140",
                "quadra": "S\/D",
                "lote": "3",
                "total_construido": 262,
                "nome_pessoa": "ROBERTO MARIO RODRIGUES MARTINS",
                "cpf": "409.036.998-34",
                "cnpj": null,
                "area_terreno": "1180.00",
                "tipo_edificacao": "Edificado",
                "tipo_utilizacao": "Residencial",
                "zona": "ZR3",
                "cat_via": " L",
                "nome_loteamento": "850180 - SUB-FERNANDO ARGENTIN",
                "imob_id_principal": 15248,
                "multiplo": 1,
                "uso_imovel": "Residencial",
                "historico": null,
                "desenho_id": 745552
            },
            {
                "id": 28327,
                "inscricao": 845180731019700,
                "imob_id": 15248,
                "logradouro": "RUA   LUDEVINA DE FREITAS",
                "numero": "100",
                "complemento": "S\/N",
                "bairro": "SALTINHO",
                "cara_quarteirao": "1140",
                "quadra": "S\/D",
                "lote": "3",
                "total_construido": 262,
                "nome_pessoa": "ROBERTO MARIO RODRIGUES MARTINS",
                "cpf": "409.036.998-34",
                "cnpj": null,
                "area_terreno": "1180.00",
                "tipo_edificacao": "Edificado",
                "tipo_utilizacao": "Residencial",
                "zona": "ZR3",
                "cat_via": " L",
                "nome_loteamento": "850180 - SUB-FERNANDO ARGENTIN",
                "imob_id_principal": 15248,
                "multiplo": 1,
                "uso_imovel": "Residencial",
                "historico": null,
                "desenho_id": 745556
            },
            {
                "id": 28327,
                "inscricao": 845180731019700,
                "imob_id": 15248,
                "logradouro": "RUA   LUDEVINA DE FREITAS",
                "numero": "100",
                "complemento": "S\/N",
                "bairro": "SALTINHO",
                "cara_quarteirao": "1140",
                "quadra": "S\/D",
                "lote": "3",
                "total_construido": 262,
                "nome_pessoa": "ROBERTO MARIO RODRIGUES MARTINS",
                "cpf": "409.036.998-34",
                "cnpj": null,
                "area_terreno": "1180.00",
                "tipo_edificacao": "Edificado",
                "tipo_utilizacao": "Residencial",
                "zona": "ZR3",
                "cat_via": " L",
                "nome_loteamento": "850180 - SUB-FERNANDO ARGENTIN",
                "imob_id_principal": 15248,
                "multiplo": 1,
                "uso_imovel": "Residencial",
                "historico": null,
                "desenho_id": 805060
            },
            {
                "id": 28328,
                "inscricao": 845180731018600,
                "imob_id": 15247,
                "logradouro": "RUA   LUDEVINA DE FREITAS",
                "numero": "90",
                "complemento": "S\/N",
                "bairro": "SALTINHO",
                "cara_quarteirao": "1140",
                "quadra": "S\/D",
                "lote": "4",
                "total_construido": 320,
                "nome_pessoa": "SINVAL JOSE BARROS.",
                "cpf": "057.496.828-89",
                "cnpj": null,
                "area_terreno": "2850.00",
                "tipo_edificacao": "Edificado",
                "tipo_utilizacao": "Residencial",
                "zona": "ZR3",
                "cat_via": " L",
                "nome_loteamento": "850180 - SUB-FERNANDO ARGENTIN",
                "imob_id_principal": 15247,
                "multiplo": 1,
                "uso_imovel": "Residencial",
                "historico": null,
                "desenho_id": 745576
            },
            {
                "id": 28328,
                "inscricao": 845180731018600,
                "imob_id": 15247,
                "logradouro": "RUA   LUDEVINA DE FREITAS",
                "numero": "90",
                "complemento": "S\/N",
                "bairro": "SALTINHO",
                "cara_quarteirao": "1140",
                "quadra": "S\/D",
                "lote": "4",
                "total_construido": 320,
                "nome_pessoa": "SINVAL JOSE BARROS.",
                "cpf": "057.496.828-89",
                "cnpj": null,
                "area_terreno": "2850.00",
                "tipo_edificacao": "Edificado",
                "tipo_utilizacao": "Residencial",
                "zona": "ZR3",
                "cat_via": " L",
                "nome_loteamento": "850180 - SUB-FERNANDO ARGENTIN",
                "imob_id_principal": 15247,
                "multiplo": 1,
                "uso_imovel": "Residencial",
                "historico": null,
                "desenho_id": 745579
            },
            {
                "id": 28328,
                "inscricao": 845180731018600,
                "imob_id": 15247,
                "logradouro": "RUA   LUDEVINA DE FREITAS",
                "numero": "90",
                "complemento": "S\/N",
                "bairro": "SALTINHO",
                "cara_quarteirao": "1140",
                "quadra": "S\/D",
                "lote": "4",
                "total_construido": 320,
                "nome_pessoa": "SINVAL JOSE BARROS.",
                "cpf": "057.496.828-89",
                "cnpj": null,
                "area_terreno": "2850.00",
                "tipo_edificacao": "Edificado",
                "tipo_utilizacao": "Residencial",
                "zona": "ZR3",
                "cat_via": " L",
                "nome_loteamento": "850180 - SUB-FERNANDO ARGENTIN",
                "imob_id_principal": 15247,
                "multiplo": 1,
                "uso_imovel": "Residencial",
                "historico": null,
                "desenho_id": 805063
            },
            {
                "id": 28333,
                "inscricao": 845180731015900,
                "imob_id": 15244,
                "logradouro": "RUA   LUDEVINA DE FREITAS",
                "numero": "60",
                "complemento": "S\/N",
                "bairro": "SALTINHO",
                "cara_quarteirao": "1140",
                "quadra": "S\/D",
                "lote": "7",
                "total_construido": 350,
                "nome_pessoa": "ARMANDO MATALLO JUNIOR.",
                "cpf": "068.706.198-91",
                "cnpj": null,
                "area_terreno": "1517.00",
                "tipo_edificacao": "Edificado",
                "tipo_utilizacao": "Residencial",
                "zona": "ZR3",
                "cat_via": " L",
                "nome_loteamento": "850180 - SUB-FERNANDO ARGENTIN",
                "imob_id_principal": 15244,
                "multiplo": 1,
                "uso_imovel": "Residencial",
                "historico": null,
                "desenho_id": 745583
            },
            {
                "id": 28333,
                "inscricao": 845180731015900,
                "imob_id": 15244,
                "logradouro": "RUA   LUDEVINA DE FREITAS",
                "numero": "60",
                "complemento": "S\/N",
                "bairro": "SALTINHO",
                "cara_quarteirao": "1140",
                "quadra": "S\/D",
                "lote": "7",
                "total_construido": 350,
                "nome_pessoa": "ARMANDO MATALLO JUNIOR.",
                "cpf": "068.706.198-91",
                "cnpj": null,
                "area_terreno": "1517.00",
                "tipo_edificacao": "Edificado",
                "tipo_utilizacao": "Residencial",
                "zona": "ZR3",
                "cat_via": " L",
                "nome_loteamento": "850180 - SUB-FERNANDO ARGENTIN",
                "imob_id_principal": 15244,
                "multiplo": 1,
                "uso_imovel": "Residencial",
                "historico": null,
                "desenho_id": 805076
            },
            {
                "id": 28334,
                "inscricao": 845180731013900,
                "imob_id": 15243,
                "logradouro": "RUA   LUDEVINA DE FREITAS",
                "numero": "40",
                "complemento": "S\/N",
                "bairro": "SALTINHO",
                "cara_quarteirao": "1140",
                "quadra": "S\/D",
                "lote": "8",
                "total_construido": 196,
                "nome_pessoa": "NEIDE DE SOUZA PERINI",
                "cpf": "569.216.918-53",
                "cnpj": null,
                "area_terreno": "1618.00",
                "tipo_edificacao": "Edificado",
                "tipo_utilizacao": "Residencial",
                "zona": "ZR3",
                "cat_via": " L",
                "nome_loteamento": "850180 - SUB-FERNANDO ARGENTIN",
                "imob_id_principal": 15243,
                "multiplo": 1,
                "uso_imovel": "Residencial",
                "historico": null,
                "desenho_id": 745584
            },
            {
                "id": 28334,
                "inscricao": 845180731013900,
                "imob_id": 15243,
                "logradouro": "RUA   LUDEVINA DE FREITAS",
                "numero": "40",
                "complemento": "S\/N",
                "bairro": "SALTINHO",
                "cara_quarteirao": "1140",
                "quadra": "S\/D",
                "lote": "8",
                "total_construido": 196,
                "nome_pessoa": "NEIDE DE SOUZA PERINI",
                "cpf": "569.216.918-53",
                "cnpj": null,
                "area_terreno": "1618.00",
                "tipo_edificacao": "Edificado",
                "tipo_utilizacao": "Residencial",
                "zona": "ZR3",
                "cat_via": " L",
                "nome_loteamento": "850180 - SUB-FERNANDO ARGENTIN",
                "imob_id_principal": 15243,
                "multiplo": 1,
                "uso_imovel": "Residencial",
                "historico": null,
                "desenho_id": 805080
            },
            {
                "id": 28334,
                "inscricao": 845180731013900,
                "imob_id": 15243,
                "logradouro": "RUA   LUDEVINA DE FREITAS",
                "numero": "40",
                "complemento": "S\/N",
                "bairro": "SALTINHO",
                "cara_quarteirao": "1140",
                "quadra": "S\/D",
                "lote": "8",
                "total_construido": 196,
                "nome_pessoa": "NEIDE DE SOUZA PERINI",
                "cpf": "569.216.918-53",
                "cnpj": null,
                "area_terreno": "1618.00",
                "tipo_edificacao": "Edificado",
                "tipo_utilizacao": "Residencial",
                "zona": "ZR3",
                "cat_via": " L",
                "nome_loteamento": "850180 - SUB-FERNANDO ARGENTIN",
                "imob_id_principal": 15243,
                "multiplo": 1,
                "uso_imovel": "Residencial",
                "historico": null,
                "desenho_id": 805122
            },
            {
                "id": 28335,
                "inscricao": 845180731012800,
                "imob_id": 15242,
                "logradouro": "RUA   LUDEVINA DE FREITAS",
                "numero": "38",
                "complemento": "S\/N",
                "bairro": "SALTINHO",
                "cara_quarteirao": "1140",
                "quadra": "S\/D",
                "lote": "9",
                "total_construido": 156,
                "nome_pessoa": "KATIA BELTRAMO",
                "cpf": "035.668.538-10",
                "cnpj": null,
                "area_terreno": "972.50",
                "tipo_edificacao": "Edificado",
                "tipo_utilizacao": "Residencial",
                "zona": "ZR3",
                "cat_via": " L",
                "nome_loteamento": "850180 - SUB-FERNANDO ARGENTIN",
                "imob_id_principal": 15242,
                "multiplo": 1,
                "uso_imovel": "Residencial",
                "historico": null,
                "desenho_id": 744534
            },
            {
                "id": 28335,
                "inscricao": 845180731012800,
                "imob_id": 15242,
                "logradouro": "RUA   LUDEVINA DE FREITAS",
                "numero": "38",
                "complemento": "S\/N",
                "bairro": "SALTINHO",
                "cara_quarteirao": "1140",
                "quadra": "S\/D",
                "lote": "9",
                "total_construido": 156,
                "nome_pessoa": "KATIA BELTRAMO",
                "cpf": "035.668.538-10",
                "cnpj": null,
                "area_terreno": "972.50",
                "tipo_edificacao": "Edificado",
                "tipo_utilizacao": "Residencial",
                "zona": "ZR3",
                "cat_via": " L",
                "nome_loteamento": "850180 - SUB-FERNANDO ARGENTIN",
                "imob_id_principal": 15242,
                "multiplo": 1,
                "uso_imovel": "Residencial",
                "historico": null,
                "desenho_id": 745555
            },
            {
                "id": 28335,
                "inscricao": 845180731012800,
                "imob_id": 15242,
                "logradouro": "RUA   LUDEVINA DE FREITAS",
                "numero": "38",
                "complemento": "S\/N",
                "bairro": "SALTINHO",
                "cara_quarteirao": "1140",
                "quadra": "S\/D",
                "lote": "9",
                "total_construido": 156,
                "nome_pessoa": "KATIA BELTRAMO",
                "cpf": "035.668.538-10",
                "cnpj": null,
                "area_terreno": "972.50",
                "tipo_edificacao": "Edificado",
                "tipo_utilizacao": "Residencial",
                "zona": "ZR3",
                "cat_via": " L",
                "nome_loteamento": "850180 - SUB-FERNANDO ARGENTIN",
                "imob_id_principal": 15242,
                "multiplo": 1,
                "uso_imovel": "Residencial",
                "historico": null,
                "desenho_id": 745557
            },
            {
                "id": 28335,
                "inscricao": 845180731012800,
                "imob_id": 15242,
                "logradouro": "RUA   LUDEVINA DE FREITAS",
                "numero": "38",
                "complemento": "S\/N",
                "bairro": "SALTINHO",
                "cara_quarteirao": "1140",
                "quadra": "S\/D",
                "lote": "9",
                "total_construido": 156,
                "nome_pessoa": "KATIA BELTRAMO",
                "cpf": "035.668.538-10",
                "cnpj": null,
                "area_terreno": "972.50",
                "tipo_edificacao": "Edificado",
                "tipo_utilizacao": "Residencial",
                "zona": "ZR3",
                "cat_via": " L",
                "nome_loteamento": "850180 - SUB-FERNANDO ARGENTIN",
                "imob_id_principal": 15242,
                "multiplo": 1,
                "uso_imovel": "Residencial",
                "historico": null,
                "desenho_id": 805084
            },
            {
                "id": 28335,
                "inscricao": 845180731012800,
                "imob_id": 15242,
                "logradouro": "RUA   LUDEVINA DE FREITAS",
                "numero": "38",
                "complemento": "S\/N",
                "bairro": "SALTINHO",
                "cara_quarteirao": "1140",
                "quadra": "S\/D",
                "lote": "9",
                "total_construido": 156,
                "nome_pessoa": "KATIA BELTRAMO",
                "cpf": "035.668.538-10",
                "cnpj": null,
                "area_terreno": "972.50",
                "tipo_edificacao": "Edificado",
                "tipo_utilizacao": "Residencial",
                "zona": "ZR3",
                "cat_via": " L",
                "nome_loteamento": "850180 - SUB-FERNANDO ARGENTIN",
                "imob_id_principal": 15242,
                "multiplo": 1,
                "uso_imovel": "Residencial",
                "historico": null,
                "desenho_id": 805117
            },
            {
                "id": 28335,
                "inscricao": 845180731012800,
                "imob_id": 15242,
                "logradouro": "RUA   LUDEVINA DE FREITAS",
                "numero": "38",
                "complemento": "S\/N",
                "bairro": "SALTINHO",
                "cara_quarteirao": "1140",
                "quadra": "S\/D",
                "lote": "9",
                "total_construido": 156,
                "nome_pessoa": "KATIA BELTRAMO",
                "cpf": "035.668.538-10",
                "cnpj": null,
                "area_terreno": "972.50",
                "tipo_edificacao": "Edificado",
                "tipo_utilizacao": "Residencial",
                "zona": "ZR3",
                "cat_via": " L",
                "nome_loteamento": "850180 - SUB-FERNANDO ARGENTIN",
                "imob_id_principal": 15242,
                "multiplo": 1,
                "uso_imovel": "Residencial",
                "historico": null,
                "desenho_id": 805121
            },
            {
                "id": 28337,
                "inscricao": 350150303009600,
                "imob_id": 15932,
                "logradouro": "PLN   ESTRADA MUNICIPAL",
                "numero": "0",
                "complemento": "S\/N",
                "bairro": "SALTINHO",
                "cara_quarteirao": "1140",
                "quadra": "S\/D",
                "lote": "S\/N",
                "total_construido": 138,
                "nome_pessoa": "LUIZ ROBERTO VOLTAN",
                "cpf": "088.021.558-52",
                "cnpj": null,
                "area_terreno": "5629.07",
                "tipo_edificacao": "Edificado",
                "tipo_utilizacao": "Residencial",
                "zona": "ZR3",
                "cat_via": " ECS2",
                "nome_loteamento": "410160 - FAZENDA SALTINHO",
                "imob_id_principal": 15932,
                "multiplo": 1,
                "uso_imovel": "Residencial",
                "historico": null,
                "desenho_id": null
            },
            {
                "id": 52330,
                "inscricao": 940230451059000,
                "imob_id": 124304,
                "logradouro": "RUA   JAGUARI",
                "numero": "590",
                "complemento": "S\/N",
                "bairro": "BONFIM",
                "cara_quarteirao": "2204",
                "quadra": "S\/D",
                "lote": "24",
                "total_construido": 95,
                "nome_pessoa": "MAURICIO PIERINI DE ALBUQUERQUE",
                "cpf": "046.711.658-05",
                "cnpj": null,
                "area_terreno": "1842.00",
                "tipo_edificacao": "Edificado",
                "tipo_utilizacao": "Residencial",
                "zona": "ZUM3",
                "cat_via": " L",
                "nome_loteamento": "420150 - SITIO S. JOSE-RIO JAGUARI",
                "imob_id_principal": 124304,
                "multiplo": 1,
                "uso_imovel": "Residencial",
                "historico": null,
                "desenho_id": null
            },
            {
                "id": 52337,
                "inscricao": 400150404010900,
                "imob_id": 15184,
                "logradouro": "RUA   JAGUARI",
                "numero": "110",
                "complemento": "S\/N",
                "bairro": "BONFIM",
                "cara_quarteirao": "2204",
                "quadra": "S\/D",
                "lote": "3",
                "total_construido": 90,
                "nome_pessoa": "OLIVAR PIMENTEL DE SOUZA",
                "cpf": "172.958.908-15",
                "cnpj": null,
                "area_terreno": "2452.50",
                "tipo_edificacao": "Edificado",
                "tipo_utilizacao": "Residencial",
                "zona": "ZUM3",
                "cat_via": " L",
                "nome_loteamento": "430155 - AREA DESM. SITIO SAO JOSE",
                "imob_id_principal": 15184,
                "multiplo": 1,
                "uso_imovel": "Residencial",
                "historico": null,
                "desenho_id": null
            },
            {
                "id": 52341,
                "inscricao": 940230451022800,
                "imob_id": 125624,
                "logradouro": "RUA   JAGUARI",
                "numero": "230",
                "complemento": "S\/N",
                "bairro": "BONFIM",
                "cara_quarteirao": "2204",
                "quadra": "S\/D",
                "lote": "7",
                "total_construido": 132,
                "nome_pessoa": "BENEDITO PEREIRA RAMOS",
                "cpf": "976.263.688-00",
                "cnpj": null,
                "area_terreno": "4032.00",
                "tipo_edificacao": "Edificado",
                "tipo_utilizacao": "Residencial",
                "zona": "ZUM3",
                "cat_via": " L",
                "nome_loteamento": "420150 - SITIO S. JOSE-RIO JAGUARI",
                "imob_id_principal": 125624,
                "multiplo": 1,
                "uso_imovel": "Residencial",
                "historico": null,
                "desenho_id": null
            },
            {
                "id": 53094,
                "inscricao": 350150303016000,
                "imob_id": 15409,
                "logradouro": "PLN   ESTRADA DA SERVIDAO",
                "numero": "0",
                "complemento": "S\/N",
                "bairro": "RECANTO DOS PASSAROS",
                "cara_quarteirao": "2255",
                "quadra": "B",
                "lote": "10A",
                "total_construido": 250,
                "nome_pessoa": "RHODIA BRASIL S.A",
                "cpf": null,
                "cnpj": "57.507.626\/0004-59",
                "area_terreno": "6851.00",
                "tipo_edificacao": "Edificado",
                "tipo_utilizacao": "Residencial",
                "zona": "ZDI3",
                "cat_via": " L",
                "nome_loteamento": "945165 - SITIO CAPIM FINO-QUILOMBO",
                "imob_id_principal": 15409,
                "multiplo": 1,
                "uso_imovel": "Residencial",
                "historico": null,
                "desenho_id": null
            },
            {
                "id": 53095,
                "inscricao": 350150303016600,
                "imob_id": 15689,
                "logradouro": "PLN   ESTRADA DA SERVIDAO",
                "numero": "0",
                "complemento": "S\/N",
                "bairro": "RECANTO DOS PASSAROS",
                "cara_quarteirao": "2255",
                "quadra": "A",
                "lote": "13",
                "total_construido": 87,
                "nome_pessoa": "ILZA MARIA MEIRELLES FAUVEL",
                "cpf": "444.188.258-00",
                "cnpj": null,
                "area_terreno": "722.00",
                "tipo_edificacao": "Edificado",
                "tipo_utilizacao": "Residencial",
                "zona": "ZDI3",
                "cat_via": " L",
                "nome_loteamento": "945165 - SITIO CAPIM FINO-QUILOMBO",
                "imob_id_principal": 15689,
                "multiplo": 2,
                "uso_imovel": "Residencial",
                "historico": null,
                "desenho_id": null
            },
            {
                "id": 53096,
                "inscricao": 945165241000600,
                "imob_id": 124311,
                "logradouro": "PLN   ESTRADA DA SERVIDAO",
                "numero": "0",
                "complemento": "S\/N",
                "bairro": "RECANTO DOS PASSAROS",
                "cara_quarteirao": "2255",
                "quadra": "A",
                "lote": "13",
                "total_construido": 64,
                "nome_pessoa": "RHODIA BRASIL S.A",
                "cpf": null,
                "cnpj": "57.507.626\/0004-59",
                "area_terreno": "1403.00",
                "tipo_edificacao": "Edificado",
                "tipo_utilizacao": "Residencial",
                "zona": "ZDI3",
                "cat_via": " L",
                "nome_loteamento": "945165 - SITIO CAPIM FINO-QUILOMBO",
                "imob_id_principal": 15689,
                "multiplo": 2,
                "uso_imovel": "Residencial",
                "historico": null,
                "desenho_id": null
            },
            {
                "id": 53099,
                "inscricao": 945165241000700,
                "imob_id": 124312,
                "logradouro": "PLN   ESTRADA DA SERVIDAO",
                "numero": "0",
                "complemento": "S\/N",
                "bairro": "RECANTO DOS PASSAROS",
                "cara_quarteirao": "2255",
                "quadra": "B",
                "lote": "15",
                "total_construido": 184,
                "nome_pessoa": "RHODIA BRASIL S.A",
                "cpf": null,
                "cnpj": "57.507.626\/0004-59",
                "area_terreno": "2968.50",
                "tipo_edificacao": "Edificado",
                "tipo_utilizacao": "Industria",
                "zona": "ZDI3",
                "cat_via": " L",
                "nome_loteamento": "945165 - SITIO CAPIM FINO-QUILOMBO",
                "imob_id_principal": 124312,
                "multiplo": 1,
                "uso_imovel": "Industria",
                "historico": null,
                "desenho_id": null
            },
            {
                "id": 53110,
                "inscricao": 350150303015800,
                "imob_id": 131851,
                "logradouro": "PLN   ESTRADA DA SERVIDAO",
                "numero": "0",
                "complemento": "S\/N",
                "bairro": "RECANTO DOS PASSAROS",
                "cara_quarteirao": "2255",
                "quadra": "B",
                "lote": "7",
                "total_construido": 174,
                "nome_pessoa": "RHODIA BRASIL S.A",
                "cpf": null,
                "cnpj": "57.507.626\/0004-59",
                "area_terreno": "1809.00",
                "tipo_edificacao": "Edificado",
                "tipo_utilizacao": "Residencial",
                "zona": "ZDI3",
                "cat_via": " L",
                "nome_loteamento": "945165 - SITIO CAPIM FINO-QUILOMBO",
                "imob_id_principal": 131851,
                "multiplo": 1,
                "uso_imovel": "Residencial",
                "historico": null,
                "desenho_id": null
            },
            {
                "id": 53112,
                "inscricao": 350150303015900,
                "imob_id": 131852,
                "logradouro": "PLN   ESTRADA DA SERVIDAO",
                "numero": "0",
                "complemento": "S\/N",
                "bairro": "RECANTO DOS PASSAROS",
                "cara_quarteirao": "2255",
                "quadra": "B",
                "lote": "8",
                "total_construido": 190,
                "nome_pessoa": "RHODIA BRASIL S.A",
                "cpf": null,
                "cnpj": "57.507.626\/0004-59",
                "area_terreno": "4451.25",
                "tipo_edificacao": "Edificado",
                "tipo_utilizacao": "Residencial",
                "zona": "ZDI3",
                "cat_via": " L",
                "nome_loteamento": "945165 - SITIO CAPIM FINO-QUILOMBO",
                "imob_id_principal": 131852,
                "multiplo": 1,
                "uso_imovel": "Residencial",
                "historico": null,
                "desenho_id": null
            },
            {
                "id": 55628,
                "inscricao": 350150303006500,
                "imob_id": 15147,
                "logradouro": "RUA   SEM DENOMINACAO",
                "numero": "0",
                "complemento": "S\/N",
                "bairro": "BONFIM",
                "cara_quarteirao": "2400",
                "quadra": "S\/D",
                "lote": "S\/N",
                "total_construido": 157016,
                "nome_pessoa": "RHODIA BRASIL S.A",
                "cpf": null,
                "cnpj": "57.507.626\/0004-59",
                "area_terreno": "3796828.99",
                "tipo_edificacao": "Edificado",
                "tipo_utilizacao": "Industria",
                "zona": "ZDI3",
                "cat_via": " L",
                "nome_loteamento": "400150 - FAZENDA SAO FRANCISCO",
                "imob_id_principal": 15147,
                "multiplo": 1,
                "uso_imovel": "Industria",
                "historico": null,
                "desenho_id": null
            },
            {
                "id": 55629,
                "inscricao": 350150303004600,
                "imob_id": 12,
                "logradouro": "PLN   ESTRADA DA SERVIDAO",
                "numero": "0",
                "complemento": "S\/N",
                "bairro": "BETEL",
                "cara_quarteirao": "9001",
                "quadra": "S\/D",
                "lote": ".",
                "total_construido": 32,
                "nome_pessoa": "ANTONIO VITORINO PERINI",
                "cpf": "820.058.858-00",
                "cnpj": null,
                "area_terreno": "4500.00",
                "tipo_edificacao": "Edificado",
                "tipo_utilizacao": "Residencial",
                "zona": "ZE",
                "cat_via": " L",
                "nome_loteamento": "350150 - BETEL",
                "imob_id_principal": 12,
                "multiplo": 1,
                "uso_imovel": "Residencial",
                "historico": null,
                "desenho_id": null
            },
            {
                "id": 55630,
                "inscricao": 350150303005000,
                "imob_id": 15142,
                "logradouro": "PLN   ESTRADA DA SERVIDAO",
                "numero": "0",
                "complemento": "S\/N",
                "bairro": "BETEL",
                "cara_quarteirao": "9002",
                "quadra": "S\/D",
                "lote": "6",
                "total_construido": 123,
                "nome_pessoa": "SERGIO ESTEVAO",
                "cpf": null,
                "cnpj": null,
                "area_terreno": "4500.00",
                "tipo_edificacao": "Edificado",
                "tipo_utilizacao": "Residencial",
                "zona": "ZE",
                "cat_via": null,
                "nome_loteamento": "350150 - BETEL",
                "imob_id_principal": 15142,
                "multiplo": 1,
                "uso_imovel": "Residencial",
                "historico": null,
                "desenho_id": null
            },
            {
                "id": 55643,
                "inscricao": 400150404007400,
                "imob_id": 15182,
                "logradouro": "EST   ESTRADA DE SERVIDAO",
                "numero": "0",
                "complemento": "S\/N",
                "bairro": "BELA VISTA",
                "cara_quarteirao": "9027",
                "quadra": "S\/D",
                "lote": "2",
                "total_construido": 96,
                "nome_pessoa": "MAICK DE SOUZA LUCIZANO",
                "cpf": "284.169.738-06",
                "cnpj": null,
                "area_terreno": "1800.00",
                "tipo_edificacao": "Edificado",
                "tipo_utilizacao": "Residencial",
                "zona": "ZUM2",
                "cat_via": " L",
                "nome_loteamento": "885165 - SITIO SANTA ROSA",
                "imob_id_principal": 15182,
                "multiplo": 1,
                "uso_imovel": "Residencial",
                "historico": null,
                "desenho_id": null
            },
            {
                "id": 55651,
                "inscricao": 945165241005900,
                "imob_id": 124687,
                "logradouro": "RUA   ANTONIO DE FREITAS",
                "numero": "228",
                "complemento": "S\/N",
                "bairro": "SALTINHO",
                "cara_quarteirao": "9035",
                "quadra": "S\/D",
                "lote": "S\/N",
                "total_construido": 316,
                "nome_pessoa": "CARLOS ANTONIO CAMARGO",
                "cpf": "017.286.598-09",
                "cnpj": null,
                "area_terreno": "6276.00",
                "tipo_edificacao": "Edificado",
                "tipo_utilizacao": "Residencial",
                "zona": "ZR3A",
                "cat_via": " L",
                "nome_loteamento": "945165 - SITIO CAPIM FINO-QUILOMBO",
                "imob_id_principal": 124687,
                "multiplo": 1,
                "uso_imovel": "Residencial",
                "historico": null,
                "desenho_id": 745549
            },
            {
                "id": 55651,
                "inscricao": 945165241005900,
                "imob_id": 124687,
                "logradouro": "RUA   ANTONIO DE FREITAS",
                "numero": "228",
                "complemento": "S\/N",
                "bairro": "SALTINHO",
                "cara_quarteirao": "9035",
                "quadra": "S\/D",
                "lote": "S\/N",
                "total_construido": 316,
                "nome_pessoa": "CARLOS ANTONIO CAMARGO",
                "cpf": "017.286.598-09",
                "cnpj": null,
                "area_terreno": "6276.00",
                "tipo_edificacao": "Edificado",
                "tipo_utilizacao": "Residencial",
                "zona": "ZR3A",
                "cat_via": " L",
                "nome_loteamento": "945165 - SITIO CAPIM FINO-QUILOMBO",
                "imob_id_principal": 124687,
                "multiplo": 1,
                "uso_imovel": "Residencial",
                "historico": null,
                "desenho_id": 745562
            },
            {
                "id": 55651,
                "inscricao": 945165241005900,
                "imob_id": 124687,
                "logradouro": "RUA   ANTONIO DE FREITAS",
                "numero": "228",
                "complemento": "S\/N",
                "bairro": "SALTINHO",
                "cara_quarteirao": "9035",
                "quadra": "S\/D",
                "lote": "S\/N",
                "total_construido": 316,
                "nome_pessoa": "CARLOS ANTONIO CAMARGO",
                "cpf": "017.286.598-09",
                "cnpj": null,
                "area_terreno": "6276.00",
                "tipo_edificacao": "Edificado",
                "tipo_utilizacao": "Residencial",
                "zona": "ZR3A",
                "cat_via": " L",
                "nome_loteamento": "945165 - SITIO CAPIM FINO-QUILOMBO",
                "imob_id_principal": 124687,
                "multiplo": 1,
                "uso_imovel": "Residencial",
                "historico": null,
                "desenho_id": 745563
            },
            {
                "id": 55651,
                "inscricao": 945165241005900,
                "imob_id": 124687,
                "logradouro": "RUA   ANTONIO DE FREITAS",
                "numero": "228",
                "complemento": "S\/N",
                "bairro": "SALTINHO",
                "cara_quarteirao": "9035",
                "quadra": "S\/D",
                "lote": "S\/N",
                "total_construido": 316,
                "nome_pessoa": "CARLOS ANTONIO CAMARGO",
                "cpf": "017.286.598-09",
                "cnpj": null,
                "area_terreno": "6276.00",
                "tipo_edificacao": "Edificado",
                "tipo_utilizacao": "Residencial",
                "zona": "ZR3A",
                "cat_via": " L",
                "nome_loteamento": "945165 - SITIO CAPIM FINO-QUILOMBO",
                "imob_id_principal": 124687,
                "multiplo": 1,
                "uso_imovel": "Residencial",
                "historico": null,
                "desenho_id": 745568
            },
            {
                "id": 55651,
                "inscricao": 945165241005900,
                "imob_id": 124687,
                "logradouro": "RUA   ANTONIO DE FREITAS",
                "numero": "228",
                "complemento": "S\/N",
                "bairro": "SALTINHO",
                "cara_quarteirao": "9035",
                "quadra": "S\/D",
                "lote": "S\/N",
                "total_construido": 316,
                "nome_pessoa": "CARLOS ANTONIO CAMARGO",
                "cpf": "017.286.598-09",
                "cnpj": null,
                "area_terreno": "6276.00",
                "tipo_edificacao": "Edificado",
                "tipo_utilizacao": "Residencial",
                "zona": "ZR3A",
                "cat_via": " L",
                "nome_loteamento": "945165 - SITIO CAPIM FINO-QUILOMBO",
                "imob_id_principal": 124687,
                "multiplo": 1,
                "uso_imovel": "Residencial",
                "historico": null,
                "desenho_id": 750452
            },
            {
                "id": 55654,
                "inscricao": 945165241005700,
                "imob_id": 124685,
                "logradouro": "RUA   ANTONIO DE FREITAS",
                "numero": "40",
                "complemento": "S\/N",
                "bairro": "SALTINHO",
                "cara_quarteirao": "9035",
                "quadra": "S\/D",
                "lote": "S\/N ",
                "total_construido": 354,
                "nome_pessoa": "WALDIR ROLLO FILHO",
                "cpf": "061.969.198-06",
                "cnpj": null,
                "area_terreno": "7000.00",
                "tipo_edificacao": "Edificado",
                "tipo_utilizacao": "Residencial",
                "zona": "ZR3",
                "cat_via": " L",
                "nome_loteamento": "945165 - SITIO CAPIM FINO-QUILOMBO",
                "imob_id_principal": 124685,
                "multiplo": 1,
                "uso_imovel": "Residencial",
                "historico": null,
                "desenho_id": 745549
            },
            {
                "id": 55654,
                "inscricao": 945165241005700,
                "imob_id": 124685,
                "logradouro": "RUA   ANTONIO DE FREITAS",
                "numero": "40",
                "complemento": "S\/N",
                "bairro": "SALTINHO",
                "cara_quarteirao": "9035",
                "quadra": "S\/D",
                "lote": "S\/N ",
                "total_construido": 354,
                "nome_pessoa": "WALDIR ROLLO FILHO",
                "cpf": "061.969.198-06",
                "cnpj": null,
                "area_terreno": "7000.00",
                "tipo_edificacao": "Edificado",
                "tipo_utilizacao": "Residencial",
                "zona": "ZR3",
                "cat_via": " L",
                "nome_loteamento": "945165 - SITIO CAPIM FINO-QUILOMBO",
                "imob_id_principal": 124685,
                "multiplo": 1,
                "uso_imovel": "Residencial",
                "historico": null,
                "desenho_id": 745562
            },
            {
                "id": 55654,
                "inscricao": 945165241005700,
                "imob_id": 124685,
                "logradouro": "RUA   ANTONIO DE FREITAS",
                "numero": "40",
                "complemento": "S\/N",
                "bairro": "SALTINHO",
                "cara_quarteirao": "9035",
                "quadra": "S\/D",
                "lote": "S\/N ",
                "total_construido": 354,
                "nome_pessoa": "WALDIR ROLLO FILHO",
                "cpf": "061.969.198-06",
                "cnpj": null,
                "area_terreno": "7000.00",
                "tipo_edificacao": "Edificado",
                "tipo_utilizacao": "Residencial",
                "zona": "ZR3",
                "cat_via": " L",
                "nome_loteamento": "945165 - SITIO CAPIM FINO-QUILOMBO",
                "imob_id_principal": 124685,
                "multiplo": 1,
                "uso_imovel": "Residencial",
                "historico": null,
                "desenho_id": 745563
            },
            {
                "id": 55654,
                "inscricao": 945165241005700,
                "imob_id": 124685,
                "logradouro": "RUA   ANTONIO DE FREITAS",
                "numero": "40",
                "complemento": "S\/N",
                "bairro": "SALTINHO",
                "cara_quarteirao": "9035",
                "quadra": "S\/D",
                "lote": "S\/N ",
                "total_construido": 354,
                "nome_pessoa": "WALDIR ROLLO FILHO",
                "cpf": "061.969.198-06",
                "cnpj": null,
                "area_terreno": "7000.00",
                "tipo_edificacao": "Edificado",
                "tipo_utilizacao": "Residencial",
                "zona": "ZR3",
                "cat_via": " L",
                "nome_loteamento": "945165 - SITIO CAPIM FINO-QUILOMBO",
                "imob_id_principal": 124685,
                "multiplo": 1,
                "uso_imovel": "Residencial",
                "historico": null,
                "desenho_id": 745568
            },
            {
                "id": 55654,
                "inscricao": 945165241005700,
                "imob_id": 124685,
                "logradouro": "RUA   ANTONIO DE FREITAS",
                "numero": "40",
                "complemento": "S\/N",
                "bairro": "SALTINHO",
                "cara_quarteirao": "9035",
                "quadra": "S\/D",
                "lote": "S\/N ",
                "total_construido": 354,
                "nome_pessoa": "WALDIR ROLLO FILHO",
                "cpf": "061.969.198-06",
                "cnpj": null,
                "area_terreno": "7000.00",
                "tipo_edificacao": "Edificado",
                "tipo_utilizacao": "Residencial",
                "zona": "ZR3",
                "cat_via": " L",
                "nome_loteamento": "945165 - SITIO CAPIM FINO-QUILOMBO",
                "imob_id_principal": 124685,
                "multiplo": 1,
                "uso_imovel": "Residencial",
                "historico": null,
                "desenho_id": 750452
            }
        ]
    }
}